indradb/__init__.py
indradb/client.py
indradb/indradb_pb2.py
indradb/indradb_pb2_grpc.py
indradb/models.py
indradb-2.0.0.dist-info/LICENSE
indradb-2.0.0.dist-info/METADATA
indradb-2.0.0.dist-info/WHEEL
indradb-2.0.0.dist-info/top_level.txt
indradb-2.0.0.dist-info/RECORD
